Metadata-Version: 2.1
Name: huspy
Version: 0.1.1
Summary: A git hooks for Python.
Author: Shawn
Maintainer: SethWen
Maintainer-email: coolrainerseth@gmail.com
License: Apache License, Version 2.0
Project-URL: Source, https://github.com/SethWen/huspy
Classifier: Development Status :: 4 - Beta
Classifier: Environment :: Console
Classifier: Intended Audience :: Developers
Classifier: License :: OSI Approved :: Apache Software License
Classifier: Operating System :: OS Independent
Classifier: Programming Language :: Python
Classifier: Programming Language :: Python :: 3.6
Classifier: Programming Language :: Python :: 3.7
Classifier: Programming Language :: Python :: 3.8
Classifier: Programming Language :: Python :: 3.9
Classifier: Programming Language :: Python :: 3.10
Classifier: Topic :: Software Development :: Libraries :: Python Modules
Classifier: Topic :: Software Development :: Quality Assurance
Provides-Extra: pyproject
License-File: LICENSE
